{"cameraMode":{"drawMode":0,"name":"Shaded","section":"Shading Mode"},"sceneLighting":true,"audioPlay":false,"sceneViewState":{"m_AlwaysRefresh":false,"showFog":true,"showSkybox":true,"showFlares":true,"showImageEffects":true,"showParticleSystems":true,"showVisualEffectGraphs":true,"m_FxEnabled":true},"in2DMode":false,"pivot":{"x":41.255149841308597,"y":0.5923125743865967,"z":1.4159303903579713},"rotation":{"x":-0.11055564880371094,"y":0.43514934182167055,"z":-0.0439968965947628,"w":-0.8939709067344666},"size":3.860809803009033,"orthographic":false}